LICENSE
README.md
flypper_redis/__init__.py
flypper_redis/storage/__init__.py
flypper_redis/storage/redis.py
flypper_redis-0.1.2.dist-info/LICENSE
flypper_redis-0.1.2.dist-info/WHEEL
flypper_redis-0.1.2.dist-info/METADATA
flypper_redis-0.1.2.dist-info/RECORD
