Metadata-Version: 2.1
Name: flypper-redis
Version: 0.1.2
Summary: Feature flags, with a GUI - Redis backend
Home-page: https://github.com/nicoolas25/flypper-redis
Author: Nicolas Zermati
Author-email: nicoolas25@gmail.com
Requires-Python: >=3.7,<4.0
Classifier: Programming Language :: Python :: 3
Classifier: Programming Language :: Python :: 3.10
Classifier: Programming Language :: Python :: 3.7
Classifier: Programming Language :: Python :: 3.8
Classifier: Programming Language :: Python :: 3.9
Requires-Dist: flypper (>=0.1.0,<0.2.0)
Requires-Dist: redis (>=3.5.3,<4.0.0)
Project-URL: Documentation, https://github.com/nicoolas25/flypper-redis
Project-URL: Repository, https://github.com/nicoolas25/flypper-redis
